thevpncompany/__init__.py
thevpncompany/consumer_openvpn_certificates.py
thevpncompany/consumer_orchestration.py
thevpncompany/vpn_is_user_valid.py
thevpncompany/zabbix_openvpn_usage_per_user.py
thevpncompany/zabbix_openvpn_user_discovery.py
thevpncompany/zabbix_track_monthly_traffic.py
thevpncompany/components/__init__.py
thevpncompany/components/macapi.py
thevpncompany/components/utils.py
thevpncompany/components/vpnapi.py
thevpncompany/test/__init__.py
thevpncompany/test/test_certificate.py
thevpncompany/test/test_orchestration.py
thevpncompany/test/test_zabbix.py
thevpncompany/test/mock/__init__.py
thevpncompany/test/mock/execute.py
thevpncompany/test/mock/response.py
thevpncompany-0.1.0.dist-info/LICENSE
thevpncompany-0.1.0.dist-info/METADATA
thevpncompany-0.1.0.dist-info/WHEEL
thevpncompany-0.1.0.dist-info/top_level.txt
thevpncompany-0.1.0.dist-info/zip-safe
thevpncompany-0.1.0.dist-info/RECORD
