Metadata-Version: 2.1
Name: thevpncompany
Version: 0.1.0
Summary: Scripts required for the open source end-to-end solution TheVPNCompany.com.au
Home-page: https://thevpncompany.com.au
Author: Ruben Rubio Rey
Author-email: ruben@thevpncompany.com.au
License: MIT
Keywords: vpn openvpn tunnel
Platform: UNKNOWN
Classifier: Development Status :: 3 - Alpha
Classifier: Intended Audience :: Developers
Classifier: Intended Audience :: Information Technology
Classifier: Intended Audience :: Science/Research
Classifier: Intended Audience :: System Administrators
Classifier: License :: OSI Approved :: MIT License
Classifier: Operating System :: POSIX
Classifier: Programming Language :: Python
Requires-Python: >=3.5
Requires-Dist: certifi (==2019.6.16)
Requires-Dist: chardet (==3.0.4)
Requires-Dist: greenstalk (==0.5.2)
Requires-Dist: idna (==2.8)
Requires-Dist: pexpect (==4.7.0)
Requires-Dist: ptyprocess (==0.6.0)
Requires-Dist: requests (==2.22.0)
Requires-Dist: urllib3 (==1.25.3)
Requires-Dist: pygments
